hrep/__init__.py
hrep/__main__.py
hrep/hexdump.py
hrep-0.4.1a0.data/scripts/hrep
hrep-0.4.1a0.dist-info/LICENSE
hrep-0.4.1a0.dist-info/METADATA
hrep-0.4.1a0.dist-info/WHEEL
hrep-0.4.1a0.dist-info/top_level.txt
hrep-0.4.1a0.dist-info/RECORD
