Metadata-Version: 2.1
Name: hrep
Version: 0.4.1a0
Summary: Binary files search utility
Home-page: https://gitlab.com/rekodah/hrep
Author: Jonathan Goren
Author-email: jonagn@gmail.com
License: MIT
Keywords: grep binary files hex search
Platform: UNKNOWN
Classifier: Development Status :: 3 - Alpha
Classifier: Topic :: Utilities
Classifier: License :: OSI Approved :: MIT License
License-File: LICENSE
Requires-Dist: scandir
Provides-Extra: all
Requires-Dist: tqdm ; extra == 'all'
